crane/__init__.py
crane/builders.py
crane/commands.py
docker_crane-0.1.0.dist-info/DESCRIPTION.rst
docker_crane-0.1.0.dist-info/entry_points.txt
docker_crane-0.1.0.dist-info/METADATA
docker_crane-0.1.0.dist-info/metadata.json
docker_crane-0.1.0.dist-info/RECORD
docker_crane-0.1.0.dist-info/top_level.txt
docker_crane-0.1.0.dist-info/WHEEL
examples/__init__.py
examples/hello_baby/__init__.py
