Metadata-Version: 2.0
Name: docker-crane
Version: 0.1.0
Summary: A simple tool for building Dockerfiles
Home-page: http://github.com/victorlin/crane
Author: Victor Lin
Author-email: bornstub@gmail.com
License: Apache 2.0
Keywords: docker dockerfile build
Platform: UNKNOWN
Requires-Dist: jinja2
Requires-Dist: click
